gw2buildutil/__init__.py
gw2buildutil/build.py
gw2buildutil/buildmod.py
gw2buildutil/buildtemplate.py
gw2buildutil/compositions.py
gw2buildutil/textbody.py
gw2buildutil/util.py
gw2buildutil/api/__init__.py
gw2buildutil/api/apiclient.py
gw2buildutil/api/client.py
gw2buildutil/api/crawl.py
gw2buildutil/api/entity.py
gw2buildutil/api/fakeclient.py
gw2buildutil/api/storage.py
gw2buildutil/api/util.py
gw2buildutil/defnfile/__init__.py
gw2buildutil/defnfile/parseutil.py
gw2buildutil/defnfile/section/__init__.py
gw2buildutil/defnfile/section/alternatives.py
gw2buildutil/defnfile/section/boonnotes.py
gw2buildutil/defnfile/section/encounters.py
gw2buildutil/defnfile/section/intro.py
gw2buildutil/defnfile/section/notes.py
gw2buildutil/defnfile/section/usage.py
gw2buildutil-0.5.1.dist-info/LICENSE
gw2buildutil-0.5.1.dist-info/METADATA
gw2buildutil-0.5.1.dist-info/WHEEL
gw2buildutil-0.5.1.dist-info/top_level.txt
gw2buildutil-0.5.1.dist-info/RECORD
