Metadata-Version: 2.1
Name: gw2buildutil
Version: 0.5.1
Summary: Python library for working with Guild Wars 2 builds
Home-page: http://ikn.org.uk/lib/gw2buildutil
Author: Joseph Lansdowne
Author-email: ikn@ikn.org.uk
Classifier: Programming Language :: Python :: 3.7
Classifier: License :: OSI Approved :: BSD License
Classifier: Operating System :: OS Independent
License-File: LICENSE
